ddcmath/__init__.py
ddcmath/actuator.py
ddcmath/airflow.py
ddcmath/electricity.py
ddcmath/exceptions.py
ddcmath/force.py
ddcmath/geometry.py
ddcmath/heating.py
ddcmath/infos.py
ddcmath/psychrometric.py
ddcmath/temperature.py
ddcmath/tolerance.py
ddcmath/ashrae/__init__.py
ddcmath/ashrae/std55/__init__.py
ddcmath/ashrae/std55/pyPMVPPD.py
ddcmath/ashrae/std55/pySET.py
ddcmath/stats/__init__.py
ddcmath/stats/charts.py
ddcmath/stats/pattern_analysis.py
ddcmath/stats/shewart_detectionlackcontrol.py
ddcmath/stats/shewhart.py
ddcmath/stats/tables.py
ddcmath-21.9.23.dist-info/LICENSE.md
ddcmath-21.9.23.dist-info/METADATA
ddcmath-21.9.23.dist-info/WHEEL
ddcmath-21.9.23.dist-info/top_level.txt
ddcmath-21.9.23.dist-info/RECORD
