Metadata-Version: 2.1
Name: ddcmath
Version: 21.9.23
Summary: Math functions related to DDC control
Home-page: https://github.com/ChristianTremblay/ddcmath
Author: Christian Tremblay, P.Eng.
Author-email: christian.tremblay@servisys.com
License: UNKNOWN
Download-URL: https://github.com/ChristianTremblay/ddcmath/archive/master.zip
Keywords: bacnet,building,automation,test
Platform: UNKNOWN
Classifier: Development Status :: 4 - Beta
Classifier: Intended Audience :: Developers
Classifier: Operating System :: OS Independent
Classifier: Programming Language :: Python
Classifier: Topic :: Software Development :: Libraries :: Python Modules
Classifier: Topic :: Utilities
License-File: LICENSE.md
Requires-Dist: pint
